streaming_helper/channel_management/__init__.py
streaming_helper/channel_management/get_published_messages.py
streaming_helper/channel_management/deribit/__init__.py
streaming_helper/channel_management/deribit/subscribing_to_channels.py
streaming_helper/data_announcer/__init__.py
streaming_helper/data_announcer/binance/__init__.py
streaming_helper/data_announcer/binance/distributing_ws_data.py
streaming_helper/data_announcer/deribit/__init__.py
streaming_helper/data_announcer/deribit/allocating_ohlc.py
streaming_helper/data_announcer/deribit/distributing_ws_data.py
streaming_helper/data_announcer/deribit/get_instrument_summary.py
streaming_helper/data_announcer/deribit/starter.py
streaming_helper/data_announcer/telegram/__init__.py
streaming_helper/data_announcer/telegram/relaying_message.py
streaming_helper/data_cleaning/__init__.py
streaming_helper/data_cleaning/app_data_cleaning.py
streaming_helper/data_cleaning/managing_closed_transactions.py
streaming_helper/data_cleaning/managing_delivered_transactions.py
streaming_helper/data_cleaning/pruning_db.py
streaming_helper/data_cleaning/reconciling_db.py
streaming_helper/data_receiver/__init__.py
streaming_helper/data_receiver/binance.py
streaming_helper/data_receiver/deribit.py
streaming_helper/db_management/__init__.py
streaming_helper/db_management/redis_client.py
streaming_helper/db_management/sqlite_management.py
streaming_helper/market_understanding/__init__.py
streaming_helper/market_understanding/price_action/__init__.py
streaming_helper/market_understanding/price_action/candles_analysis.py
streaming_helper/restful_api/__init__.py
streaming_helper/restful_api/connector.py
streaming_helper/restful_api/binance/__init__.py
streaming_helper/restful_api/binance/api_url_end_point.toml
streaming_helper/restful_api/binance/binance.py
streaming_helper/restful_api/binance/download_binance.py
streaming_helper/restful_api/deribit/__init__.py
streaming_helper/restful_api/deribit/end_point_params_template.py
streaming_helper-0.1.145.dist-info/METADATA
streaming_helper-0.1.145.dist-info/WHEEL
streaming_helper-0.1.145.dist-info/RECORD
